rulog/Client.py
rulog/Device.py
rulog/Encoder.py
rulog/Error.py
rulog/ErrorRubika.py
rulog/GetDataMethod.py
rulog/GtM.py
rulog/PostData.py
rulog/RSA_ENC.py
rulog/Zedcontent.py
rulog/__init__.py
rulog/platform.py
rulog-1.0.1.dist-info/METADATA
rulog-1.0.1.dist-info/WHEEL
rulog-1.0.1.dist-info/top_level.txt
rulog-1.0.1.dist-info/RECORD
