Metadata-Version: 2.4
Name: rulog
Version: 1.0.1
Summary: Rubika: A Python library for interacting with the Rubika Login APi. 
Home-page: https://github.com/Mahdy-Ahmadi/rulog
Author: Mahdi Ahmadi
Author-email: mahdiahmadi.1208@gmail.com
Maintainer: Mahdi Ahmadi
Maintainer-email: mahdiahmadi.1208@gmail.com
License: MIT
Project-URL: Bug Tracker, https://t.me/Bprogrammer
Project-URL: Documentation, https://github.com/Mahdy-Ahmadi/rulog/
Project-URL: Source Code, https://github.com/Mahdy-Ahmadi/rulog/tree/main/rulog
Keywords: rubika bot api library chat messaging rubpy pyrubi rubigram rubika_bot rubika_api fast_rub
Classifier: Development Status :: 5 - Production/Stable
Classifier: Intended Audience :: Developers
Classifier: Programming Language :: Python :: 3
Classifier: Programming Language :: Python :: 3.8
Classifier: Programming Language :: Python :: 3.9
Classifier: Programming Language :: Python :: 3.10
Classifier: License :: OSI Approved :: MIT License
Classifier: Operating System :: OS Independent
Classifier: Topic :: Communications :: Chat
Classifier: Topic :: Software Development :: Libraries
Classifier: Natural Language :: Persian
Requires-Python: >=3.6
Requires-Dist: Pillow
Requires-Dist: pycryptodome
Requires-Dist: aiohttp
Requires-Dist: httpx
Dynamic: author
Dynamic: author-email
Dynamic: classifier
Dynamic: description
Dynamic: description-content-type
Dynamic: home-page
Dynamic: keywords
Dynamic: license
Dynamic: maintainer
Dynamic: maintainer-email
Dynamic: project-url
Dynamic: requires-dist
Dynamic: requires-python
Dynamic: summary
